fwg.cpython-36m-darwin.so
fwg-0.2.11.dist-info/METADATA
fwg-0.2.11.dist-info/WHEEL
fwg-0.2.11.dist-info/top_level.txt
fwg-0.2.11.dist-info/RECORD
