Metadata-Version: 2.1
Name: fwg
Version: 0.2.11
Summary: Fast sliced wasserstein distance matrix computation
Home-page: UNKNOWN
Author: Thomas Ricatte
Author-email: UNKNOWN
License: UNKNOWN
Platform: UNKNOWN
Requires-Dist: numpy
